[
    {
        "id": 1,
        "citizenship_type": "PRIMARY",
        "country_id": 840,
        "de_person_id": 1
    },
    {
        "id": 2,
        "citizenship_type": "PRIMARY",
        "country_id": 840,
        "de_person_id": 2
    },
    {
        "id": 3,
        "citizenship_type": "PRIMARY",
        "country_id": 840,
        "de_person_id": 3
    },
    {
        "id": 4,
        "citizenship_type": "PRIMARY",
        "country_id": 840,
        "de_person_id": 4
    },
    {
        "id": 5,
        "citizenship_type": "PRIMARY",
        "country_id": 840,
        "de_person_id": 5
    },
    {
        "id": 6,
        "citizenship_type": "PRIMARY",
        "country_id": 840,
        "de_person_id": 6
    },
    {
        "id": 7,
        "citizenship_type": "PRIMARY",
        "country_id": 840,
        "de_person_id": 7
    },
    {
        "id": 8,
        "citizenship_type": "PRIMARY",
        "country_id": 840,
        "de_person_id": 8
    },
    {
        "id": 9,
        "citizenship_type": "PRIMARY",
        "country_id": 840,
        "de_person_id": 9
    },
    {
        "id": 10,
        "citizenship_type": "PRIMARY",
        "country_id": 840,
        "de_person_id": 10
    },
    {
        "id": 11,
        "citizenship_type": "PRIMARY",
        "country_id": 840,
        "de_person_id": 11
    },
    {
        "id": 12,
        "citizenship_type": "PRIMARY",
        "country_id": 840,
        "de_person_id": 12
    },
    {
        "id": 13,
        "citizenship_type": "PRIMARY",
        "country_id": 840,
        "de_person_id": 13
    },
    {
        "id": 14,
        "citizenship_type": "PRIMARY",
        "country_id": 840,
        "de_person_id": 14
    },
    {
        "id": 15,
        "citizenship_type": "PRIMARY",
        "country_id": 840,
        "de_person_id": 15
    },
    {
        "id": 16,
        "citizenship_type": "PRIMARY",
        "country_id": 840,
        "de_person_id": 16
    },
    {
        "id": 17,
        "citizenship_type": "PRIMARY",
        "country_id": 840,
        "de_person_id": 17
    },
    {
        "id": 18,
        "citizenship_type": "PRIMARY",
        "country_id": 840,
        "de_person_id": 18
    },
    {
        "id": 19,
        "citizenship_type": "PRIMARY",
        "country_id": 840,
        "de_person_id": 19
    },
    {
        "id": 20,
        "citizenship_type": "PRIMARY",
        "country_id": 840,
        "de_person_id": 20
    },
    {
        "id": 21,
        "citizenship_type": "PRIMARY",
        "country_id": 840,
        "de_person_id": 21
    },
    {
        "id": 22,
        "citizenship_type": "PRIMARY",
        "country_id": 840,
        "de_person_id": 22
    },
    {
        "id": 23,
        "citizenship_type": "PRIMARY",
        "country_id": 840,
        "de_person_id": 23
    },
    {
        "id": 24,
        "citizenship_type": "PRIMARY",
        "country_id": 840,
        "de_person_id": 24
    },
    {
        "id": 25,
        "citizenship_type": "PRIMARY",
        "country_id": 840,
        "de_person_id": 25
    },
    {
        "id": 26,
        "citizenship_type": "PRIMARY",
        "country_id": 840,
        "de_person_id": 26
    },
    {
        "id": 27,
        "citizenship_type": "PRIMARY",
        "country_id": 840,
        "de_person_id": 27
    },
    {
        "id": 28,
        "citizenship_type": "PRIMARY",
        "country_id": 840,
        "de_person_id": 28
    },
    {
        "id": 29,
        "citizenship_type": "PRIMARY",
        "country_id": 840,
        "de_person_id": 29
    },
    {
        "id": 30,
        "citizenship_type": "PRIMARY",
        "country_id": 840,
        "de_person_id": 30
    },
    {
        "id": 31,
        "citizenship_type": "PRIMARY",
        "country_id": 840,
        "de_person_id": 31
    },
    {
        "id": 32,
        "citizenship_type": "PRIMARY",
        "country_id": 840,
        "de_person_id": 32
    },
    {
        "id": 33,
        "citizenship_type": "PRIMARY",
        "country_id": 840,
        "de_person_id": 33
    },
    {
        "id": 34,
        "citizenship_type": "PRIMARY",
        "country_id": 840,
        "de_person_id": 34
    },
    {
        "id": 35,
        "citizenship_type": "PRIMARY",
        "country_id": 840,
        "de_person_id": 35
    },
    {
        "id": 36,
        "citizenship_type": "PRIMARY",
        "country_id": 840,
        "de_person_id": 36
    },
    {
        "id": 37,
        "citizenship_type": "PRIMARY",
        "country_id": 840,
        "de_person_id": 37
    },
    {
        "id": 38,
        "citizenship_type": "PRIMARY",
        "country_id": 840,
        "de_person_id": 38
    },
    {
        "id": 39,
        "citizenship_type": "PRIMARY",
        "country_id": 840,
        "de_person_id": 39
    },
    {
        "id": 40,
        "citizenship_type": "PRIMARY",
        "country_id": 840,
        "de_person_id": 40
    },
    {
        "id": 41,
        "citizenship_type": "PRIMARY",
        "country_id": 840,
        "de_person_id": 41
    },
    {
        "id": 42,
        "citizenship_type": "PRIMARY",
        "country_id": 840,
        "de_person_id": 42
    },
    {
        "id": 43,
        "citizenship_type": "PRIMARY",
        "country_id": 840,
        "de_person_id": 43
    },
    {
        "id": 44,
        "citizenship_type": "PRIMARY",
        "country_id": 840,
        "de_person_id": 44
    },
    {
        "id": 45,
        "citizenship_type": "PRIMARY",
        "country_id": 840,
        "de_person_id": 45
    },
    {
        "id": 46,
        "citizenship_type": "PRIMARY",
        "country_id": 840,
        "de_person_id": 46
    },
    {
        "id": 47,
        "citizenship_type": "PRIMARY",
        "country_id": 840,
        "de_person_id": 47
    },
    {
        "id": 48,
        "citizenship_type": "PRIMARY",
        "country_id": 840,
        "de_person_id": 48
    },
    {
        "id": 49,
        "citizenship_type": "PRIMARY",
        "country_id": 840,
        "de_person_id": 49
    },
    {
        "id": 50,
        "citizenship_type": "PRIMARY",
        "country_id": 840,
        "de_person_id": 50
    },
    {
        "id": 51,
        "citizenship_type": "PRIMARY",
        "country_id": 840,
        "de_person_id": 51
    },
    {
        "id": 52,
        "citizenship_type": "PRIMARY",
        "country_id": 840,
        "de_person_id": 52
    },
    {
        "id": 53,
        "citizenship_type": "PRIMARY",
        "country_id": 840,
        "de_person_id": 53
    },
    {
        "id": 54,
        "citizenship_type": "PRIMARY",
        "country_id": 840,
        "de_person_id": 54
    },
    {
        "id": 55,
        "citizenship_type": "PRIMARY",
        "country_id": 840,
        "de_person_id": 55
    },
    {
        "id": 56,
        "citizenship_type": "PRIMARY",
        "country_id": 840,
        "de_person_id": 56
    },
    {
        "id": 57,
        "citizenship_type": "PRIMARY",
        "country_id": 840,
        "de_person_id": 57
    },
    {
        "id": 58,
        "citizenship_type": "PRIMARY",
        "country_id": 840,
        "de_person_id": 58
    },
    {
        "id": 59,
        "citizenship_type": "PRIMARY",
        "country_id": 840,
        "de_person_id": 59
    },
    {
        "id": 60,
        "citizenship_type": "PRIMARY",
        "country_id": 840,
        "de_person_id": 60
    },
    {
        "id": 61,
        "citizenship_type": "PRIMARY",
        "country_id": 840,
        "de_person_id": 61
    },
    {
        "id": 62,
        "citizenship_type": "PRIMARY",
        "country_id": 840,
        "de_person_id": 62
    },
    {
        "id": 63,
        "citizenship_type": "PRIMARY",
        "country_id": 840,
        "de_person_id": 63
    },
    {
        "id": 64,
        "citizenship_type": "PRIMARY",
        "country_id": 840,
        "de_person_id": 64
    },
    {
        "id": 65,
        "citizenship_type": "PRIMARY",
        "country_id": 840,
        "de_person_id": 65
    },
    {
        "id": 66,
        "citizenship_type": "PRIMARY",
        "country_id": 840,
        "de_person_id": 66
    },
    {
        "id": 67,
        "citizenship_type": "PRIMARY",
        "country_id": 840,
        "de_person_id": 67
    },
    {
        "id": 68,
        "citizenship_type": "PRIMARY",
        "country_id": 840,
        "de_person_id": 68
    },
    {
        "id": 69,
        "citizenship_type": "PRIMARY",
        "country_id": 840,
        "de_person_id": 69
    },
    {
        "id": 70,
        "citizenship_type": "PRIMARY",
        "country_id": 840,
        "de_person_id": 70
    },
    {
        "id": 71,
        "citizenship_type": "PRIMARY",
        "country_id": 840,
        "de_person_id": 71
    },
    {
        "id": 72,
        "citizenship_type": "PRIMARY",
        "country_id": 840,
        "de_person_id": 72
    },
    {
        "id": 73,
        "citizenship_type": "PRIMARY",
        "country_id": 840,
        "de_person_id": 73
    },
    {
        "id": 74,
        "citizenship_type": "PRIMARY",
        "country_id": 840,
        "de_person_id": 74
    },
    {
        "id": 75,
        "citizenship_type": "PRIMARY",
        "country_id": 840,
        "de_person_id": 75
    },
    {
        "id": 76,
        "citizenship_type": "PRIMARY",
        "country_id": 840,
        "de_person_id": 76
    },
    {
        "id": 77,
        "citizenship_type": "PRIMARY",
        "country_id": 840,
        "de_person_id": 77
    },
    {
        "id": 78,
        "citizenship_type": "PRIMARY",
        "country_id": 840,
        "de_person_id": 78
    },
    {
        "id": 79,
        "citizenship_type": "PRIMARY",
        "country_id": 840,
        "de_person_id": 79
    }
]